jmagics-0.1.0.dist-info/METADATA
jmagics-0.1.0.dist-info/WHEEL
jmagics-0.1.0.dist-info/entry_points.txt
jmagics/__init__.py
jmagics-0.1.0.dist-info/RECORD
